otel_instrumenter/__init__.py
otel_instrumenter/otel.py
otel_instrumenter-0.1.1.dist-info/METADATA
otel_instrumenter-0.1.1.dist-info/WHEEL
otel_instrumenter-0.1.1.dist-info/top_level.txt
otel_instrumenter-0.1.1.dist-info/RECORD
