Metadata-Version: 2.4
Name: otel-instrumenter
Version: 0.1.1
Summary: Reusable package to configure OpenTelemetry in Python apps
Requires-Python: >=3.13
Requires-Dist: grpcio>=1.73.1
Requires-Dist: opentelemetry-exporter-otlp-proto-grpc>=1.35.0
Requires-Dist: opentelemetry-instrumentation-fastapi>=0.56b0
Requires-Dist: opentelemetry-instrumentation-httpx>=0.56b0
Requires-Dist: opentelemetry-sdk>=1.35.0
Requires-Dist: protobuf>=6.31.1
